fireeyeapicms
