Metadata-Version: 1.0
Name: fireeyeapicms
Version: 0.3
Summary: UNKNOWN
Home-page: https://github.com/aaronjonen/fireeyeapi
Author: aaron jonen
Author-email: aaron.jonen@nexteraenergy.com
License: MIT
Platform: UNKNOWN
